static_ffmpeg/__init__.py
static_ffmpeg/_add_paths.py
static_ffmpeg/run.py
static_ffmpeg-2.12.dist-info/licenses/LICENSE
static_ffmpeg-2.12.dist-info/METADATA
static_ffmpeg-2.12.dist-info/WHEEL
static_ffmpeg-2.12.dist-info/entry_points.txt
static_ffmpeg-2.12.dist-info/top_level.txt
static_ffmpeg-2.12.dist-info/RECORD
