Metadata-Version: 2.4
Name: static_ffmpeg
Version: 2.12
Summary: Cross platform ffmpeg to work on various systems.
Author-email: Zach Vorhies <dont@email.me>
License: MIT
Classifier: License :: OSI Approved :: MIT License
Classifier: Programming Language :: Python :: 3.6
Classifier: Programming Language :: Python :: 3.9
Classifier: Operating System :: Microsoft :: Windows
Classifier: Operating System :: POSIX
Classifier: Operating System :: MacOS :: MacOS X
Classifier: Environment :: Console
Requires-Python: >=3.6.0
License-File: LICENSE
Requires-Dist: requests
Requires-Dist: filelock
Requires-Dist: progress
Requires-Dist: twine>=3.8.0
Provides-Extra: test
Requires-Dist: pytest; extra == "test"
Dynamic: license-file
